mutenix/__init__.py
mutenix/__main__.py
mutenix/config.py
mutenix/hid_commands.py
mutenix/hid_device.py
mutenix/macropad.py
mutenix/package.py
mutenix/teams_messages.py
mutenix/tray_icon.py
mutenix/version.py
mutenix/virtual_macropad.py
mutenix/web_server.py
mutenix/websocket_client.py
mutenix/assets/icon_active_16.png
mutenix/assets/icon_active_32.png
mutenix/assets/icon_active_64.png
mutenix/assets/icon_active_apple_touch.png
mutenix/assets/icon_all_red_16.png
mutenix/assets/icon_all_red_32.png
mutenix/assets/icon_all_red_64.png
mutenix/assets/icon_all_red_apple_touch.png
mutenix/assets/icon_inactive_16.png
mutenix/assets/icon_inactive_32.png
mutenix/assets/icon_inactive_64.png
mutenix/assets/icon_inactive_apple_touch.png
mutenix/assets/mutenix.ico
mutenix/assets/mutenix_logo_finalicon_active.eps
mutenix/assets/mutenix_logo_finalicon_active.pdf
mutenix/assets/mutenix_logo_finalicon_active.png
mutenix/assets/mutenix_logo_finalicon_active.svg
mutenix/assets/mutenix_logo_finalicon_all_red.eps
mutenix/assets/mutenix_logo_finalicon_all_red.pdf
mutenix/assets/mutenix_logo_finalicon_all_red.png
mutenix/assets/mutenix_logo_finalicon_all_red.svg
mutenix/assets/mutenix_logo_finalicon_inactive.eps
mutenix/assets/mutenix_logo_finalicon_inactive.pdf
mutenix/assets/mutenix_logo_finalicon_inactive.png
mutenix/assets/mutenix_logo_finalicon_inactive.svg
mutenix/assets/mutenix_logo_finallogo_active.eps
mutenix/assets/mutenix_logo_finallogo_active.pdf
mutenix/assets/mutenix_logo_finallogo_active.png
mutenix/assets/mutenix_logo_finallogo_active.svg
mutenix/assets/mutenix_logo_finallogo_inactive.eps
mutenix/assets/mutenix_logo_finallogo_inactive.pdf
mutenix/assets/mutenix_logo_finallogo_inactive.png
mutenix/assets/mutenix_logo_finallogo_inactive.svg
mutenix/assets/mutenix_logo_finallogo_vertical.eps
mutenix/assets/mutenix_logo_finallogo_vertical.pdf
mutenix/assets/mutenix_logo_finallogo_vertical.png
mutenix/assets/mutenix_logo_finallogo_vertical.svg
mutenix-0.5.10.dist-info/METADATA
mutenix-0.5.10.dist-info/WHEEL
mutenix-0.5.10.dist-info/entry_points.txt
mutenix-0.5.10.dist-info/licenses/LICENSE
mutenix-0.5.10.dist-info/RECORD
