Metadata-Version: 2.4
Name: mutenix
Version: 0.5.10
Summary: Mutenix host software for the Mutenix macropad
Project-URL: Homepage, https://mutenix.de
Project-URL: Documentation, https://mutenix.de/docs/host
Project-URL: Repository, https://github.com/mutenix-org/software-host
Project-URL: Issues, https://github.com/mutenix-org/software-host/issues
Author-email: Matthias Bilger <matthias@bilger.info>
License-Expression: MIT
License-File: LICENSE
Keywords: keyboard,macroboard,remote,teams
Classifier: Development Status :: 4 - Beta
Classifier: Intended Audience :: Developers
Classifier: Intended Audience :: End Users/Desktop
Classifier: Programming Language :: Python :: 3.12
Classifier: Topic :: Utilities
Requires-Python: >=3.12
Requires-Dist: aiohttp-jinja2>=1.6
Requires-Dist: aiohttp>=3.11.11
Requires-Dist: daiquiri>=3.3.0
Requires-Dist: hidapi>=0.14.0.post4
Requires-Dist: markdown>=3.7
Requires-Dist: psutil>=6.1.1
Requires-Dist: pydantic>=2.10.4
Requires-Dist: pynput>=1.7.7
Requires-Dist: pystray>=0.19.5
Requires-Dist: pytest-asyncio>=0.25.0
Requires-Dist: python-minifier>=2.11.3
Requires-Dist: pywin32; platform_system == 'Windows'
Requires-Dist: pywinauto; platform_system == 'Windows'
Requires-Dist: pyyaml>=6.0.2
Requires-Dist: requests>=2.32.3
Requires-Dist: semver>=3.0.2
Requires-Dist: tqdm>=4.67.1
Requires-Dist: types-requests>=2.32.0.20241016
Requires-Dist: websockets>=14.1
